pythonCSVutils/__init__.py
pythonCSVutils/csv_processor.py
pythonCSVutils/setup.py
pythonCSVutils/test.py
pythonCSVutils-0.1.1.dist-info/METADATA
pythonCSVutils-0.1.1.dist-info/WHEEL
pythonCSVutils-0.1.1.dist-info/top_level.txt
pythonCSVutils-0.1.1.dist-info/RECORD
