Metadata-Version: 2.1
Name: pythonCSVutils
Version: 0.1.1
Summary: A Python module for processing CSV files efficiently
Classifier: Programming Language :: Python :: 3
Classifier: License :: OSI Approved :: MIT License
Classifier: Operating System :: OS Independent
